setup.py
vrep/__init__.py
vrep/client.py
vrep/mobile.py
vrep/sensor.py
vrep/core/__init__.py
vrep/core/model.py
vrep/core/remoteApi.dll
vrep/core/remoteApi.dylib
vrep/core/remoteApi.so
vrep/core/vrep.py
vrep/core/vrepConst.py
vrep_python.egg-info/PKG-INFO
vrep_python.egg-info/SOURCES.txt
vrep_python.egg-info/dependency_links.txt
vrep_python.egg-info/requires.txt
vrep_python.egg-info/top_level.txt