Metadata-Version: 1.0
Name: vrep-python
Version: 0.4
Summary: b'vrep python library'
Home-page: http://github.com/cpak00/vrep-python
Author: chenyiming
Author-email: cymcpak00@gmail.com
License: Free
Keywords: vrep,python
Platform: any
